tikbot/__init__.py
tikbot/__main__.py
tikbot/apiros.py
tikbot/config.py
tikbot/handler/__init__.py
tikbot/handler/command/__init__.py
tikbot/handler/command/ping.py
tikbot/handler/command/start.py
tikbot/version.py
tikbot-0.1.0.dist-info/LICENSE
tikbot-0.1.0.dist-info/WHEEL
tikbot-0.1.0.dist-info/METADATA
tikbot-0.1.0.dist-info/RECORD
